CHANGES.rst
MANIFEST.in
README.rst
bootstrap.py
buildout.cfg
setup.py
etc/settings.ini
etc/settings.ini.in
src/pwt/__init__.py
src/pwt.jinja2js.egg-info/PKG-INFO
src/pwt.jinja2js.egg-info/SOURCES.txt
src/pwt.jinja2js.egg-info/dependency_links.txt
src/pwt.jinja2js.egg-info/entry_points.txt
src/pwt.jinja2js.egg-info/namespace_packages.txt
src/pwt.jinja2js.egg-info/not-zip-safe
src/pwt.jinja2js.egg-info/requires.txt
src/pwt.jinja2js.egg-info/top_level.txt
src/pwt/jinja2js/__init__.py
src/pwt/jinja2js/app.py
src/pwt/jinja2js/cli.py
src/pwt/jinja2js/environment.py
src/pwt/jinja2js/jscompiler.py
src/pwt/jinja2js/nodes.py
src/pwt/jinja2js/nose_test_suites.py
src/pwt/jinja2js/tests.py
src/pwt/jinja2js/wsgi.py
src/pwt/jinja2js/goog/base.js
src/pwt/jinja2js/media/soyutils.js
src/pwt/jinja2js/media/soyutils_usegoog.js
src/pwt/jinja2js/media/tests.js
src/pwt/jinja2js/media/compiled/c9bd78bbdd9f3616a798fc7d48b6c666.js
src/pwt/jinja2js/templates/autoescaped.jinja2
src/pwt/jinja2js/templates/call.jinja2
src/pwt/jinja2js/templates/documentation.jinja2
src/pwt/jinja2js/templates/documentation_concat.jinja2
src/pwt/jinja2js/templates/filters.jinja2
src/pwt/jinja2js/templates/for.jinja2
src/pwt/jinja2js/templates/if.jinja2
src/pwt/jinja2js/templates/import.jinja2
src/pwt/jinja2js/templates/imported.jinja2
src/pwt/jinja2js/templates/index.html
src/pwt/jinja2js/templates/tests.html
src/pwt/jinja2js/templates/tests_compiled.html
src/pwt/jinja2js/templates/tests_concat.html
src/pwt/jinja2js/templates/variables.jinja2
src/pwt/jinja2js/test_templates/example.jinja2
src/pwt/jinja2js/test_templates/test_import.jinja2