Metadata-Version: 1.1
Name: pwt.jinja2js
Version: 0.8.1
Summary: 
